docs/source/__init__.py
docs/source/conf.py
dvtTestKit-0.2.9.data/scripts/dvtTestKit.cmd
dvtTestKit-0.2.9.data/scripts/post.cmd
dvttestkit/__init__.py
dvttestkit/confluence_handler.py
dvttestkit/data_handler.py
dvttestkit/gdrive_handler.py
dvttestkit/jenkins_handler.py
dvttestkit/jira_handler.py
dvttestkit/post.py
dvttestkit/slack_handler.py
dvttestkit/testKitUtils.py
dvttestkit/test_monitor_handler.py
dvtTestKit-0.2.9.dist-info/METADATA
dvtTestKit-0.2.9.dist-info/WHEEL
dvtTestKit-0.2.9.dist-info/entry_points.txt
dvtTestKit-0.2.9.dist-info/top_level.txt
dvtTestKit-0.2.9.dist-info/RECORD
