Metadata-Version: 2.1
Name: dvtTestKit
Version: 0.2.9
Summary: Toolkit for DVT testing
Author: Dan.Edens
Author-email: Danedens31@gmail.com
Requires-Python: >=3.9
Requires-Dist: paho-mqtt
Requires-Dist: slack-sdk
Requires-Dist: jira
Requires-Dist: pyshorteners
Requires-Dist: pexpect
Requires-Dist: netmiko
Requires-Dist: requests
Requires-Dist: bs4
Requires-Dist: wheel
Requires-Dist: sphinxcontrib.confluencebuilder
